{
  "game_id": "39055c2d-b531-4ceb-b76f-0092609b5505",
  "events": [
    {
      "timestamp": "2025-11-03T17:13:28.397922",
      "type": "game_start",
      "data": {
        "players": [
          {
            "player_id": 1,
            "name": "玩家1",
            "color": "#ef4444",
            "is_ai": false,
            "resources": {
              "wood": 4,
              "brick": 4,
              "sheep": 2,
              "wheat": 2,
              "ore": 2
            },
            "resource_count": 14,
            "buildings": [],
            "victory_points": 0,
            "roads_left": 15,
            "settlements_left": 5,
            "cities_left": 4,
            "has_longest_road": false,
            "has_largest_army": false
          },
          {
            "player_id": 2,
            "name": "玩家2",
            "color": "#3b82f6",
            "is_ai": false,
            "resources": {
              "wood": 4,
              "brick": 4,
              "sheep": 2,
              "wheat": 2,
              "ore": 2
            },
            "resource_count": 14,
            "buildings": [],
            "victory_points": 0,
            "roads_left": 15,
            "settlements_left": 5,
            "cities_left": 4,
            "has_longest_road": false,
            "has_largest_army": false
          },
          {
            "player_id": 3,
            "name": "AI对手1",
            "color": "#10b981",
            "is_ai": true,
            "resources": {
              "wood": 4,
              "brick": 4,
              "sheep": 2,
              "wheat": 2,
              "ore": 2
            },
            "resource_count": 14,
            "buildings": [],
            "victory_points": 0,
            "roads_left": 15,
            "settlements_left": 5,
            "cities_left": 4,
            "has_longest_road": false,
            "has_largest_army": false
          },
          {
            "player_id": 4,
            "name": "AI对手2",
            "color": "#f59e0b",
            "is_ai": true,
            "resources": {
              "wood": 4,
              "brick": 4,
              "sheep": 2,
              "wheat": 2,
              "ore": 2
            },
            "resource_count": 14,
            "buildings": [],
            "victory_points": 0,
            "roads_left": 15,
            "settlements_left": 5,
            "cities_left": 4,
            "has_longest_road": false,
            "has_largest_army": false
          }
        ],
        "map_seed": 0
      }
    },
    {
      "timestamp": "2025-11-03T17:13:31.046022",
      "type": "player_toggle_ai",
      "data": {
        "player_id": 2,
        "is_ai": true
      }
    },
    {
      "timestamp": "2025-11-03T17:13:40.981538",
      "type": "turn_end",
      "data": {
        "player_id": 1,
        "round_number": 1
      }
    },
    {
      "timestamp": "2025-11-03T17:13:42.346683",
      "type": "dice_roll",
      "data": {
        "player_id": 2,
        "dice1": 4,
        "dice2": 2,
        "total": 6
      }
    }
  ]
}